junkpy/__init__.py
junkpy/base.py
junkpy/extensions.py
junkpy/type_processors.py
junkpy-0.4.3.dist-info/LICENSE.txt
junkpy-0.4.3.dist-info/METADATA
junkpy-0.4.3.dist-info/WHEEL
junkpy-0.4.3.dist-info/top_level.txt
junkpy-0.4.3.dist-info/RECORD
