Metadata-Version: 2.1
Name: junkpy
Version: 0.4.3
Summary: Library for processing Junk configuration files
Author: Samoxiaki
Author-email: samoxiaki@yahoo.com
License: GNU GENERAL PUBLIC LICENSE
Requires-Python: >=3.12
License-File: LICENSE.txt
Requires-Dist: pydantic
Requires-Dist: lark
